copycat/__init__.py
copycat/ad_copy_evaluator.py
copycat/ad_copy_evaluator_test.py
copycat/ad_copy_generator.py
copycat/ad_copy_generator_test.py
copycat/copycat.py
copycat/copycat_test.py
copycat/google_ads.py
copycat/google_ads_test.py
copycat/keyword_organiser.py
copycat/keyword_organiser_test.py
copycat/style_guide.py
copycat/style_guide_test.py
copycat/testing_utils.py
copycat/testing_utils_test.py
copycat/data/__init__.py
copycat/data/mock_gspread.py
copycat/data/mock_gspread_test.py
copycat/data/sheets.py
copycat/data/sheets_test.py
copycat/data/utils.py
copycat/data/utils_test.py
copycat/data/demo_data/existing_ads.csv
copycat/data/demo_data/extra_instructions.csv
copycat/data/demo_data/new_keywords.csv
copycat/ui/__init__.py
copycat/ui/components.py
copycat/ui/event_handlers.py
copycat/ui/generate_ads_page.py
copycat/ui/main.py
copycat/ui/new_instance_page.py
copycat/ui/prepare_data_page.py
copycat/ui/setup_page.py
copycat/ui/states.py
copycat/ui/style_guide_page.py
copycat/ui/styles.py
copycat/ui/sub_pages.py
gtech_copycat-0.0.9.dist-info/METADATA
gtech_copycat-0.0.9.dist-info/WHEEL
gtech_copycat-0.0.9.dist-info/top_level.txt
gtech_copycat-0.0.9.dist-info/RECORD
