Metadata-Version: 2.4
Name: gtech-copycat
Version: 0.0.9
Summary: Package for generating Google Search Ad Copies with AI that match the style of existing ads.
Home-page: https://github.com/google-marketing-solutions/copycat
Author: Google gTech Ads
License: Apache 2.0
Classifier: Development Status :: 3 - Alpha
Classifier: Intended Audience :: Developers
Classifier: Intended Audience :: Science/Research
Classifier: License :: OSI Approved :: Apache Software License
Classifier: Programming Language :: Python :: 3.10
Requires-Python: >=3.10
Requires-Dist: numpy
Requires-Dist: pandas>=2.1.0
Requires-Dist: google-cloud-aiplatform
Requires-Dist: scikit-learn
Requires-Dist: pydantic>=2.0.0
Requires-Dist: tenacity
Requires-Dist: tqdm
Requires-Dist: bs4
Provides-Extra: ui
Requires-Dist: mesop; extra == "ui"
Requires-Dist: gspread; extra == "ui"
Requires-Dist: google-auth; extra == "ui"
Provides-Extra: google-sheets
Requires-Dist: gspread; extra == "google-sheets"
Requires-Dist: google-auth; extra == "google-sheets"
Dynamic: author
Dynamic: classifier
Dynamic: description
Dynamic: description-content-type
Dynamic: home-page
Dynamic: license
Dynamic: provides-extra
Dynamic: requires-dist
Dynamic: requires-python
Dynamic: summary
